http_router/__init__.py
http_router/exceptions.py
http_router/py.typed
http_router/router.c
http_router/router.cpython-310-aarch64-linux-gnu.so
http_router/router.pxd
http_router/router.py
http_router/router.pyx
http_router/routes.c
http_router/routes.cpython-310-aarch64-linux-gnu.so
http_router/routes.pxd
http_router/routes.py
http_router/routes.pyx
http_router/types.py
http_router/utils.py
http_router-6.0.0.dist-info/METADATA
http_router-6.0.0.dist-info/WHEEL
http_router-6.0.0.dist-info/top_level.txt
http_router-6.0.0.dist-info/RECORD
