Metadata-Version: 2.4
Name: http-router
Version: 6.0.0
Summary: A simple router system for HTTP applications
Author-email: Kirill Klenov <horneds@gmail.com>
License: MIT License
Project-URL: homepage, https://github.com/klen/http-router
Project-URL: repository, https://github.com/klen/http-router
Project-URL: documentation, https://github.com/klen/http-router
Keywords: http,router,web,framework
Classifier: Development Status :: 5 - Production/Stable
Classifier: Intended Audience :: Developers
Classifier: License :: OSI Approved :: MIT License
Classifier: Programming Language :: Python
Classifier: Programming Language :: Python :: 3
Classifier: Programming Language :: Python :: 3.10
Classifier: Programming Language :: Python :: 3.11
Classifier: Programming Language :: Python :: 3.12
Classifier: Programming Language :: Python :: 3.13
Classifier: Programming Language :: Python :: 3.14
Classifier: Programming Language :: Python :: Implementation :: PyPy
Classifier: Programming Language :: Cython
Classifier: Topic :: Internet :: WWW/HTTP
Requires-Python: >=3.9
Provides-Extra: tests
Requires-Dist: ruff; extra == "tests"
Requires-Dist: pytest; extra == "tests"
Requires-Dist: pytest-benchmark; extra == "tests"
Requires-Dist: pytest-mypy; implementation_name == "cpython" and extra == "tests"
Provides-Extra: dev
Requires-Dist: bump2version; extra == "dev"
Requires-Dist: tox; extra == "dev"
Requires-Dist: pre-commit; extra == "dev"
